Metadata-Version: 1.0
Name: MideDistribution
Version: 0.1
Summary: Gaussian and binomial distributions
Home-page: UNKNOWN
Author: Midecreative
Author-email: adesoba5@gmail.com
License: UNKNOWN
Platform: UNKNOWN
